[{"title":"Asakusa Arc","slug":"Asakusa_Arc","thumbnail":"/images/Asakusa_Arc_(anime).png"},{"title":"Entertainment District Arc","slug":"Entertainment_District_Arc","thumbnail":"/images/Entertainment_District_Arc.png"},{"title":"Final Battle Arc","slug":"Final_Battle_Arc","thumbnail":"/images/Kimetsu_no_Yaiba_CH193.png"},{"title":"Final Selection Arc","slug":"Final_Selection_Arc","thumbnail":"/images/Final_Selection_Arc_(anime).png"},{"title":"First Mission Arc","slug":"First_Mission_Arc","thumbnail":"/images/First_Mission_Arc_(anime).png"},{"title":"Hashira Training Arc","slug":"Hashira_Training_Arc","thumbnail":"/images/Hashira_Training_Arc.png"},{"title":"Infinity Castle Arc","slug":"Infinity_Castle_Arc","thumbnail":"/images/Infinity_Castle_Arc.png"},{"title":"Mugen Train Arc","slug":"Mugen_Train_Arc","thumbnail":"/images/Mugen_Train_Arc.png"},{"title":"Natagumo Mountain Arc","slug":"Natagumo_Mountain_Arc","thumbnail":"/images/Natagumo_Mountain_Arc_(anime).png"},{"title":"Rehabilitation Training Arc","slug":"Rehabilitation_Training_Arc","thumbnail":"/images/Rehabilitation_Training_Arc_(anime).png"},{"title":"Story Arcs","slug":"Story_Arcs","thumbnail":"/images/Kimetsu_no_Yaiba_Key_Visual_2.png"},{"title":"Sunrise Countdown Arc","slug":"Sunrise_Countdown_Arc","thumbnail":"/images/Kimetsu_no_Yaiba_CH182.png"},{"title":"Swordsmith Village Arc","slug":"Swordsmith_Village_Arc","thumbnail":"/images/Swordsmith_Village_Arc.png"},{"title":"Tsuzumi Mansion Arc","slug":"Tsuzumi_Mansion_Arc","thumbnail":"/images/Tsuzumi_Mansion_Arc_(anime).png"}]